CHANGES.txt
MANIFEST.in
README.rst
setup.py
isotoma/__init__.py
isotoma.django.bootstrap.egg-info/PKG-INFO
isotoma.django.bootstrap.egg-info/SOURCES.txt
isotoma.django.bootstrap.egg-info/dependency_links.txt
isotoma.django.bootstrap.egg-info/entry_points.txt
isotoma.django.bootstrap.egg-info/namespace_packages.txt
isotoma.django.bootstrap.egg-info/not-zip-safe
isotoma.django.bootstrap.egg-info/requires.txt
isotoma.django.bootstrap.egg-info/top_level.txt
isotoma/django/__init__.py
isotoma/django/bootstrap/__init__.py
isotoma/django/bootstrap/templates/MANIFEST.tmpl
isotoma/django/bootstrap/templates/production.tmpl
isotoma/django/bootstrap/templates/settings.tmpl
isotoma/django/bootstrap/templates/setup.tmpl
isotoma/django/bootstrap/templates/staging.tmpl
isotoma/django/bootstrap/templates/urls.tmpl