Metadata-Version: 1.0
Name: isotoma.django.bootstrap
Version: 0.0.2
Summary: Bootstrap a django project to isotoma code standards
Home-page: http://github.com/isotoma/isotoma.django.bootstrap
Author: Tom Wardill
Author-email: tom.wardill@isotoma.com
License: Apache Software License
Keywords: django project bootstrap
Platform: UNKNOWN
Classifier: Intended Audience :: Developers
Classifier: Operating System :: POSIX
Classifier: License :: OSI Approved :: Apache Software License
